cellcutter/__init__.py
cellcutter/cli.py
cellcutter/cut.py
cellcutter/utils.py
cellcutter-0.2.12.dist-info/licenses/LICENSE
cellcutter-0.2.12.dist-info/METADATA
cellcutter-0.2.12.dist-info/WHEEL
cellcutter-0.2.12.dist-info/entry_points.txt
cellcutter-0.2.12.dist-info/top_level.txt
cellcutter-0.2.12.dist-info/RECORD
