Metadata-Version: 2.4
Name: cellcutter
Version: 0.2.12
Summary: cellcutter is a Python module for creating thumbnail images of cells given a multi-channel TIFF image and segmentation mask
Home-page: https://github.com/labsyspharm/cellcutter
Author: Clemens Hug
License: MIT
Requires-Python: >=3.8
License-File: LICENSE
Requires-Dist: scikit-image
Requires-Dist: numpy
Requires-Dist: pandas
Requires-Dist: tifffile
Requires-Dist: zarr<=2.14.0
Requires-Dist: numcodecs
Dynamic: license-file
